flattableanalysis/__init__.py
flattableanalysis/flat_table_analysis.py
flattableanalysis/utils.py
flattableanalysis-0.0.2.dist-info/LICENSE
flattableanalysis-0.0.2.dist-info/METADATA
flattableanalysis-0.0.2.dist-info/WHEEL
flattableanalysis-0.0.2.dist-info/RECORD
